MANIFEST.in
README.txt
setup.py
c2/__init__.py
c2.app.downloaduser.egg-info/PKG-INFO
c2.app.downloaduser.egg-info/SOURCES.txt
c2.app.downloaduser.egg-info/dependency_links.txt
c2.app.downloaduser.egg-info/entry_points.txt
c2.app.downloaduser.egg-info/namespace_packages.txt
c2.app.downloaduser.egg-info/not-zip-safe
c2.app.downloaduser.egg-info/requires.txt
c2.app.downloaduser.egg-info/top_level.txt
c2/app/__init__.py
c2/app/downloaduser/__init__.py
c2/app/downloaduser/configure.zcml
c2/app/downloaduser/event.py
c2/app/downloaduser/interfaces.py
c2/app/downloaduser/record.py
c2/app/downloaduser/version.txt
c2/app/downloaduser/browser/__init__.py
c2/app/downloaduser/browser/configure.zcml
c2/app/downloaduser/browser/downloadusers.pt
c2/app/downloaduser/browser/downloadusers.py
c2/app/downloaduser/profiles/default/metadata.xml
c2/app/downloaduser/tests/__init__.py
c2/app/downloaduser/tests/test_setup.py
docs/HISTORY.txt
docs/INSTALL.txt
docs/LICENSE.GPL
docs/LICENSE.txt