Metadata-Version: 1.0
Name: c2.app.downloaduser
Version: 1.0b1
Summary: This product is cam view username for getting download file
Home-page: http://www.cmscom.jp
Author: Manabu TERADA
Author-email: terada@cmscom.jp
License: GPL
Keywords: plone download user
Platform: UNKNOWN
Classifier: Framework :: Plone
Classifier: Programming Language :: Python
